LICENSE
MANIFEST.in
README.rst
buildout.cfg
requirements.txt
setup.py
version.txt
bob/__init__.py
bob.db.rimoner3.egg-info/PKG-INFO
bob.db.rimoner3.egg-info/SOURCES.txt
bob.db.rimoner3.egg-info/dependency_links.txt
bob.db.rimoner3.egg-info/entry_points.txt
bob.db.rimoner3.egg-info/not-zip-safe
bob.db.rimoner3.egg-info/requires.txt
bob.db.rimoner3.egg-info/top_level.txt
bob/db/__init__.py
bob/db/rimoner3/__init__.py
bob/db/rimoner3/checkfiles.py
bob/db/rimoner3/create.py
bob/db/rimoner3/driver.py
bob/db/rimoner3/models.py
bob/db/rimoner3/query.py
bob/db/rimoner3/rimoner3_db_default_cup.json
bob/db/rimoner3/rimoner3_db_default_od.json
bob/db/rimoner3/rimoner3_test_cup.csv
bob/db/rimoner3/rimoner3_test_od.csv
bob/db/rimoner3/rimoner3_train_cup.csv
bob/db/rimoner3/rimoner3_train_od.csv
bob/db/rimoner3/test.py
doc/guide.rst
doc/index.rst
doc/links.rst
doc/py_api.rst
doc/img/bob-128x128.png
doc/img/bob-favicon.ico
doc/img/bob-logo.png